{"chunk_definitions":[{"row":9,"row_count":1,"visible":true,"expansion_state":0,"options":{"engine":"r","label":"setup","include":false},"document_id":"DE5702F0","chunk_id":"csetup_chunk","chunk_label":"setup"},{"row":27,"row_count":1,"visible":true,"expansion_state":0,"options":{"engine":"r","label":"unnamed-chunk-95"},"document_id":"DE5702F0","chunk_id":"czf67phxl6ez9","chunk_label":"unnamed-chunk-1"},{"row":38,"row_count":1,"visible":true,"expansion_state":0,"options":{"engine":"r","label":"unnamed-chunk-99"},"document_id":"DE5702F0","chunk_id":"cf0yqq6g0vq1e","chunk_label":"unnamed-chunk-2"},{"row":65,"row_count":1,"visible":true,"expansion_state":0,"options":{"engine":"r","label":"unnamed-chunk-130"},"document_id":"DE5702F0","chunk_id":"csws9jm9e098j","chunk_label":"unnamed-chunk-3"},{"row":75,"row_count":1,"visible":true,"expansion_state":0,"options":{"engine":"r","label":"unnamed-chunk-132"},"document_id":"DE5702F0","chunk_id":"ccbr22vdx4o2v","chunk_label":"unnamed-chunk-4"},{"row":107,"row_count":1,"visible":true,"expansion_state":0,"options":{"engine":"r","label":"unnamed-chunk-143"},"document_id":"DE5702F0","chunk_id":"chh2yksgl7ve6","chunk_label":"unnamed-chunk-5"},{"row":140,"row_count":1,"visible":true,"expansion_state":0,"options":{"engine":"r","label":"unnamed-chunk-150"},"document_id":"DE5702F0","chunk_id":"c76b7nyfdrgy8","chunk_label":"unnamed-chunk-6"}],"doc_write_time":1616172570,"working_dir":null,"default_chunk_options":{"echo":true},"chunk_rendered_width":505}